README.rst
setup.cfg
setup.py
ptb/__init__.py
ptb/__main__.py
ptb/ptb.py
ptb.egg-info/PKG-INFO
ptb.egg-info/SOURCES.txt
ptb.egg-info/dependency_links.txt
ptb.egg-info/pbr.json
ptb.egg-info/requires.txt
ptb.egg-info/top_level.txt