Metadata-Version: 1.1
Name: ptb
Version: 0.0.3
Summary: ptb - Python TraceBack for Humans
Home-page: https://github.com/chillaranand/ptb
Author: Anand Reddy Pandikunta
Author-email: anand21nanda@gmail.com
License: UNKNOWN
Keywords: traceback debugging
Platform: UNKNOWN
Classifier: Development Status :: 1 - Planning
Classifier: Operating System :: POSIX
Classifier: Programming Language :: Python
Classifier: Programming Language :: Python :: 2.7
Classifier: Programming Language :: Python :: 3
Classifier: Programming Language :: Python :: 3.3
Classifier: Programming Language :: Python :: 3.4
Classifier: Intended Audience :: Developers
Classifier: Topic :: Software Development :: Libraries :: Python Modules
Classifier: Topic :: Utilities
